<annotation>\n\t<folder>coins</folder>\n\t<filename>IMG_20190129_163728.jpg</filename>\n\t<path>C:\\SourceCode\\Final-Year-Project\\Images\\prototype_images\\coins\\IMG_20190129_163728.jpg</path>\n\t<source>\n\t\t<database>Unknown</database>\n\t</source>\n\t<size>\n\t\t<width>1200</width>\n\t\t<height>674</height>\n\t\t<depth>3</depth>\n\t</size>\n\t<segmented>0</segmented>\n\t<object>\n\t\t<name>Five Cent</name>\n\t\t<pose>Unspecified</pose>\n\t\t<truncated>0</truncated>\n\t\t<difficult>0</difficult>\n\t\t<bndbox>\n\t\t\t<xmin>138</xmin>\n\t\t\t<ymin>76</ymin>\n\t\t\t<xmax>424</xmax>\n\t\t\t<ymax>238</ymax>\n\t\t</bndbox>\n\t</object>\n\t<object>\n\t\t<name>Twenty Cent</name>\n\t\t<pose>Unspecified</pose>\n\t\t<truncated>0</truncated>\n\t\t<difficult>0</difficult>\n\t\t<bndbox>\n\t\t\t<xmin>624</xmin>\n\t\t\t<ymin>250</ymin>\n\t\t\t<xmax>976</xmax>\n\t\t\t<ymax>516</ymax>\n\t\t</bndbox>\n\t</object>\n\t<object>\n\t\t<name>Fifty Cent</name>\n\t\t<pose>Unspecified</pose>\n\t\t<truncated>0</truncated>\n\t\t<difficult>0</difficult>\n\t\t<bndbox>\n\t\t\t<xmin>242</xmin>\n\t\t\t<ymin>290</ymin>\n\t\t\t<xmax>622</xmax>\n\t\t\t<ymax>516</ymax>\n\t\t</bndbox>\n\t</object>\n\t<object>\n\t\t<name>One Euro</name>\n\t\t<pose>Unspecified</pose>\n\t\t<truncated>0</truncated>\n\t\t<difficult>0</difficult>\n\t\t<bndbox>\n\t\t\t<xmin>476</xmin>\n\t\t\t<ymin>78</ymin>\n\t\t\t<xmax>742</xmax>\n\t\t\t<ymax>258</ymax>\n\t\t</bndbox>\n\t</object>\n\t<object>\n\t\t<name>Two Euro</name>\n\t\t<pose>Unspecified</pose>\n\t\t<truncated>0</truncated>\n\t\t<difficult>0</difficult>\n\t\t<bndbox>\n\t\t\t<xmin>238</xmin>\n\t\t\t<ymin>120</ymin>\n\t\t\t<xmax>624</xmax>\n\t\t\t<ymax>356</ymax>\n\t\t</bndbox>\n\t</object>\n</annotation>