<annotation>
	<folder>fingers</folder>
	<filename>Human_Hand.jpg</filename>
	<path>C:\SourceCode\Final-Year-Project\Images\prototype_images\fingers\Human_Hand.jpg</path>
	<source>
		<database>Unknown</database>
	</source>
	<size>
		<width>1024</width>
		<height>768</height>
		<depth>3</depth>
	</size>
	<segmented>0</segmented>
	<object>
		<name>finger</name>
		<pose>Unspecified</pose>
		<truncated>0</truncated>
		<difficult>0</difficult>
		<bndbox>
			<xmin>322</xmin>
			<ymin>141</ymin>
			<xmax>499</xmax>
			<ymax>306</ymax>
		</bndbox>
	</object>
	<object>
		<name>finger</name>
		<pose>Unspecified</pose>
		<truncated>0</truncated>
		<difficult>0</difficult>
		<bndbox>
			<xmin>413</xmin>
			<ymin>166</ymin>
			<xmax>663</xmax>
			<ymax>326</ymax>
		</bndbox>
	</object>
	<object>
		<name>finger</name>
		<pose>Unspecified</pose>
		<truncated>0</truncated>
		<difficult>0</difficult>
		<bndbox>
			<xmin>481</xmin>
			<ymin>233</ymin>
			<xmax>790</xmax>
			<ymax>378</ymax>
		</bndbox>
	</object>
	<object>
		<name>finger</name>
		<pose>Unspecified</pose>
		<truncated>0</truncated>
		<difficult>0</difficult>
		<bndbox>
			<xmin>505</xmin>
			<ymin>321</ymin>
			<xmax>843</xmax>
			<ymax>444</ymax>
		</bndbox>
	</object>
</annotation>
