<annotation>
	<folder>fingers</folder>
	<filename>lead_720_405.jpg</filename>
	<path>C:\SourceCode\Final-Year-Project\Images\prototype_images\fingers\lead_720_405.jpg</path>
	<source>
		<database>Unknown</database>
	</source>
	<size>
		<width>720</width>
		<height>405</height>
		<depth>3</depth>
	</size>
	<segmented>0</segmented>
	<object>
		<name>finger</name>
		<pose>Unspecified</pose>
		<truncated>0</truncated>
		<difficult>0</difficult>
		<bndbox>
			<xmin>207</xmin>
			<ymin>67</ymin>
			<xmax>268</xmax>
			<ymax>275</ymax>
		</bndbox>
	</object>
	<object>
		<name>finger</name>
		<pose>Unspecified</pose>
		<truncated>0</truncated>
		<difficult>0</difficult>
		<bndbox>
			<xmin>267</xmin>
			<ymin>70</ymin>
			<xmax>344</xmax>
			<ymax>245</ymax>
		</bndbox>
	</object>
	<object>
		<name>finger</name>
		<pose>Unspecified</pose>
		<truncated>0</truncated>
		<difficult>0</difficult>
		<bndbox>
			<xmin>312</xmin>
			<ymin>197</ymin>
			<xmax>357</xmax>
			<ymax>252</ymax>
		</bndbox>
	</object>
	<object>
		<name>finger</name>
		<pose>Unspecified</pose>
		<truncated>0</truncated>
		<difficult>0</difficult>
		<bndbox>
			<xmin>352</xmin>
			<ymin>223</ymin>
			<xmax>385</xmax>
			<ymax>288</ymax>
		</bndbox>
	</object>
	<object>
		<name>finger</name>
		<pose>Unspecified</pose>
		<truncated>0</truncated>
		<difficult>0</difficult>
		<bndbox>
			<xmin>376</xmin>
			<ymin>135</ymin>
			<xmax>428</xmax>
			<ymax>285</ymax>
		</bndbox>
	</object>
	<object>
		<name>finger</name>
		<pose>Unspecified</pose>
		<truncated>0</truncated>
		<difficult>0</difficult>
		<bndbox>
			<xmin>373</xmin>
			<ymin>79</ymin>
			<xmax>464</xmax>
			<ymax>246</ymax>
		</bndbox>
	</object>
	<object>
		<name>finger</name>
		<pose>Unspecified</pose>
		<truncated>0</truncated>
		<difficult>0</difficult>
		<bndbox>
			<xmin>428</xmin>
			<ymin>41</ymin>
			<xmax>499</xmax>
			<ymax>233</ymax>
		</bndbox>
	</object>
	<object>
		<name>finger</name>
		<pose>Unspecified</pose>
		<truncated>0</truncated>
		<difficult>0</difficult>
		<bndbox>
			<xmin>470</xmin>
			<ymin>68</ymin>
			<xmax>543</xmax>
			<ymax>229</ymax>
		</bndbox>
	</object>
</annotation>
