<annotation>\n\t<folder>coins</folder>\n\t<filename>IMG_20190129_140802.jpg</filename>\n\t<path>C:\\SourceCode\\Final-Year-Project\\Images\\prototype_images\\coins\\IMG_20190129_140802.jpg</path>\n\t<source>\n\t\t<database>Unknown</database>\n\t</source>\n\t<size>\n\t\t<width>1200</width>\n\t\t<height>674</height>\n\t\t<depth>3</depth>\n\t</size>\n\t<segmented>0</segmented>\n\t<object>\n\t\t<name>Five Cent</name>\n\t\t<pose>Unspecified</pose>\n\t\t<truncated>0</truncated>\n\t\t<difficult>0</difficult>\n\t\t<bndbox>\n\t\t\t<xmin>386</xmin>\n\t\t\t<ymin>236</ymin>\n\t\t\t<xmax>540</xmax>\n\t\t\t<ymax>396</ymax>\n\t\t</bndbox>\n\t</object>\n\t<object>\n\t\t<name>Ten Cent</name>\n\t\t<pose>Unspecified</pose>\n\t\t<truncated>0</truncated>\n\t\t<difficult>0</difficult>\n\t\t<bndbox>\n\t\t\t<xmin>538</xmin>\n\t\t\t<ymin>204</ymin>\n\t\t\t<xmax>696</xmax>\n\t\t\t<ymax>332</ymax>\n\t\t</bndbox>\n\t</object>\n\t<object>\n\t\t<name>Twenty Cent</name>\n\t\t<pose>Unspecified</pose>\n\t\t<truncated>0</truncated>\n\t\t<difficult>0</difficult>\n\t\t<bndbox>\n\t\t\t<xmin>528</xmin>\n\t\t\t<ymin>26</ymin>\n\t\t\t<xmax>678</xmax>\n\t\t\t<ymax>166</ymax>\n\t\t</bndbox>\n\t</object>\n\t<object>\n\t\t<name>Fifty Cent</name>\n\t\t<pose>Unspecified</pose>\n\t\t<truncated>0</truncated>\n\t\t<difficult>0</difficult>\n\t\t<bndbox>\n\t\t\t<xmin>644</xmin>\n\t\t\t<ymin>150</ymin>\n\t\t\t<xmax>812</xmax>\n\t\t\t<ymax>308</ymax>\n\t\t</bndbox>\n\t</object>\n\t<object>\n\t\t<name>One Euro</name>\n\t\t<pose>Unspecified</pose>\n\t\t<truncated>0</truncated>\n\t\t<difficult>0</difficult>\n\t\t<bndbox>\n\t\t\t<xmin>460</xmin>\n\t\t\t<ymin>316</ymin>\n\t\t\t<xmax>638</xmax>\n\t\t\t<ymax>462</ymax>\n\t\t</bndbox>\n\t</object>\n\t<object>\n\t\t<name>Two Euro</name>\n\t\t<pose>Unspecified</pose>\n\t\t<truncated>0</truncated>\n\t\t<difficult>0</difficult>\n\t\t<bndbox>\n\t\t\t<xmin>398</xmin>\n\t\t\t<ymin>368</ymin>\n\t\t\t<xmax>606</xmax>\n\t\t\t<ymax>564</ymax>\n\t\t</bndbox>\n\t</object>\n</annotation>